github_skills/__init__.py
github_skills/bin.py
github_skills/exceptions.py
github_skills/github.py
github_skills/tests/__init__.py
github_skills/tests/conftest.py
github_skills/tests/test_get_skills.py
github_skills-1.0.2.dist-info/DESCRIPTION.rst
github_skills-1.0.2.dist-info/METADATA
github_skills-1.0.2.dist-info/RECORD
github_skills-1.0.2.dist-info/WHEEL
github_skills-1.0.2.dist-info/entry_points.txt
github_skills-1.0.2.dist-info/metadata.json
github_skills-1.0.2.dist-info/top_level.txt
